backmusic/main.py
backmusic/player.py
backmusic-0.3.dist-info/LICENSE
backmusic-0.3.dist-info/METADATA
backmusic-0.3.dist-info/WHEEL
backmusic-0.3.dist-info/entry_points.txt
backmusic-0.3.dist-info/top_level.txt
backmusic-0.3.dist-info/RECORD
