Metadata-Version: 2.1
Name: backmusic
Version: 0.3
Summary: back_music_player  Its Extract audio url from video and play in background.
Home-page: https://github.com/ScRiPt1337/back_music_player
Author: script1337
Author-email: anon42237@gmail.com
License: MIT
Platform: UNKNOWN
Classifier: License :: OSI Approved :: MIT License
Classifier: Programming Language :: Python :: 3
Classifier: Programming Language :: Python :: 3.8
Requires-Dist: argparse
Requires-Dist: clint
Requires-Dist: playsound
Requires-Dist: pynput
Requires-Dist: youtube-dl
